canitalk/__init__.py
canitalk-0.0.1.dist-info/LICENSE
canitalk-0.0.1.dist-info/METADATA
canitalk-0.0.1.dist-info/WHEEL
canitalk-0.0.1.dist-info/top_level.txt
canitalk-0.0.1.dist-info/RECORD
