Metadata-Version: 2.1
Name: canitalk
Version: 0.0.1
Summary: A small package based on codeforces Boy or Girl problem
Author-email: Burhan Uddin <burhan8.314@protonmail.com>
Project-URL: Homepage, https://gitlab.com/burhan8314/canitalk
Project-URL: Issues, https://gitlab.com/burhan8314/canitalk/-/issues
Classifier: Programming Language :: Python :: 3
Classifier: Operating System :: OS Independent
Requires-Python: >=3.8
License-File: LICENSE
